README
setup.py
lunch/__init__.py
lunch/commands.py
lunch/dialogs.py
lunch/graph.py
lunch/gui.py
lunch/logger.py
lunch/master.py
lunch/runner.py
lunch/sig.py
lunch/states.py
lunch.egg-info/PKG-INFO
lunch.egg-info/SOURCES.txt
lunch.egg-info/dependency_links.txt
lunch.egg-info/top_level.txt
scripts/lunch
scripts/lunch-slave