Metadata-Version: 1.0
Name: lunch
Version: 0.6.0
Summary: The Lunch Distributed Process Launcher
Home-page: http://code.sat.qc.ca/redmine/projects/lunch
Author: SAT
Author-email: alexandre@quessy.net
License: UNKNOWN
Platform: UNKNOWN
